cbox/__init__.py
cbox/__main__.py
cbox/cli.py
cbox/cliparser.py
cbox/concurrency.py
cbox/executors.py
cbox/streams.py
cbox/utils.py
cbox-0.5.0.dist-info/DESCRIPTION.rst
cbox-0.5.0.dist-info/METADATA
cbox-0.5.0.dist-info/RECORD
cbox-0.5.0.dist-info/WHEEL
cbox-0.5.0.dist-info/entry_points.txt
cbox-0.5.0.dist-info/metadata.json
cbox-0.5.0.dist-info/top_level.txt
