Metadata-Version: 2.0
Name: cbox
Version: 0.5.0
Summary: convert any python function to unix-style command
Home-page: https://github.com/shmuelamar/cbox
Author: Shmuel Amar
Author-email: UNKNOWN
License: MIT
Keywords: unix command pipes cli
Platform: UNKNOWN
Classifier: Development Status :: 4 - Beta
Classifier: License :: OSI Approved :: MIT License
Classifier: Programming Language :: Python :: 3.5
Classifier: Programming Language :: Python :: 3.6
Classifier: Programming Language :: Python :: 3.7
Classifier: Programming Language :: Python :: 3 :: Only
Classifier: Intended Audience :: Developers
Classifier: Intended Audience :: System Administrators
Classifier: Intended Audience :: Information Technology
Classifier: Operating System :: OS Independent
